README.rst
journalwatch.py
setup.py
journalwatch.egg-info/PKG-INFO
journalwatch.egg-info/SOURCES.txt
journalwatch.egg-info/dependency_links.txt
journalwatch.egg-info/entry_points.txt
journalwatch.egg-info/top_level.txt