Metadata-Version: 1.1
Name: journalwatch
Version: 1.0.1
Summary: A tool to get notified on error messages in the systemd journal
Home-page: http://git.the-compiler.org/journalwatch/
Author: Florian Bruhin
Author-email: me@the-compiler.org
License: GPL
Keywords: systemd journal journald logwatch logcheck
Platform: UNKNOWN
Classifier: Development Status :: 4 - Beta
Classifier: Environment :: Console
Classifier: Intended Audience :: System Administrators
Classifier: License :: OSI Approved :: GNU General Public License v3 or later (GPLv3+)
Classifier: Natural Language :: English
Classifier: Operating System :: POSIX :: Linux
Classifier: Programming Language :: Python :: 3
Classifier: Topic :: System
Classifier: Topic :: System :: Boot :: Init
Classifier: Topic :: System :: Logging
Classifier: Topic :: System :: Systems Administration
Classifier: Topic :: Utilities
